mixpanel_extract-0.1.dist-info/RECORD
mixpanel_extract-0.1.dist-info/top_level.txt
mixpanel_extract-0.1.dist-info/METADATA
mixpanel_extract-0.1.dist-info/WHEEL
mixpanel_extract-0.1.dist-info/entry_points.txt
mixpanel_extract-0.1.dist-info/DESCRIPTION.rst
mixpanel_extract-0.1.dist-info/metadata.json
mixpanel_extract/commands.py
mixpanel_extract/tests.py
mixpanel_extract/process.py
mixpanel_extract/__init__.py
