Metadata-Version: 2.0
Name: mixpanel-extract
Version: 0.1
Summary: Extract Mixpanel raw events and store on S3
Home-page: https://github.com/pior/mixpanel-extract
Author: Pior Bastida    
Author-email: pior@pbastida.net
License: GPLv2
Keywords: mixpanel s3 etl
Platform: UNKNOWN
Requires-Dist: boto
